OT_knn/OT_knn.py
OT_knn/__init__.py
OT_knn/data_process.py
ot_knn-0.1.4.dist-info/METADATA
ot_knn-0.1.4.dist-info/WHEEL
ot_knn-0.1.4.dist-info/top_level.txt
ot_knn-0.1.4.dist-info/RECORD
